{
    "_links": {
        "self": {
            "href": "http:\/\/default\/admin\/appearance\/font\/5563?_format=hal_json"
        },
        "type": {
            "href": "http:\/\/drupal.org\/rest\/type\/font\/font"
        },
        "http:\/\/drupal.org\/rest\/relation\/font\/font\/field_classification": [
            {
                "href": "http:\/\/default\/taxonomy\/term\/4?_format=hal_json"
            }
        ],
        "http:\/\/drupal.org\/rest\/relation\/font\/font\/field_supported_languages": [
            {
                "href": "http:\/\/default\/taxonomy\/term\/5?_format=hal_json"
            }
        ]
    },
    "fid": [
        {
            "value": 5563
        }
    ],
    "uuid": [
        {
            "value": "25b7523d-8ed4-481d-b12d-6351f3684a6c"
        }
    ],
    "pid": [
        {
            "value": "google_fonts_api"
        }
    ],
    "url": [
        {
            "value": "https:\/\/www.google.com\/webfonts\/family?family=Expletus Sans&subset=latin#500italic"
        }
    ],
    "name": [
        {
            "value": "Expletus Sans 500italic (latin)"
        }
    ],
    "css_family": [
        {
            "value": "Expletus Sans"
        }
    ],
    "css_style": [
        {
            "value": "italic"
        }
    ],
    "css_weight": [
        {
            "value": "500"
        }
    ],
    "metadata": [
        {
            "value": "a:2:{s:4:\"path\";s:23:\"Expletus Sans:500italic\";s:6:\"subset\";s:5:\"latin\";}"
        }
    ],
    "created": [
        {
            "value": "2019-07-01T22:35:48+00:00",
            "format": "Y-m-d\\TH:i:sP"
        }
    ],
    "changed": [
        {
            "value": "2019-07-01T22:35:48+00:00",
            "format": "Y-m-d\\TH:i:sP"
        }
    ],
    "status": [
        {
            "value": false,
            "lang": "und"
        }
    ],
    "_embedded": {
        "http:\/\/drupal.org\/rest\/relation\/font\/font\/field_classification": [
            {
                "_links": {
                    "self": {
                        "href": "http:\/\/default\/taxonomy\/term\/4?_format=hal_json"
                    },
                    "type": {
                        "href": "http:\/\/drupal.org\/rest\/type\/taxonomy_term\/font_classification"
                    }
                },
                "uuid": [
                    {
                        "value": "e1d25a54-1e14-4aa4-bfbf-d5bc9573bf7b"
                    }
                ]
            }
        ],
        "http:\/\/drupal.org\/rest\/relation\/font\/font\/field_supported_languages": [
            {
                "_links": {
                    "self": {
                        "href": "http:\/\/default\/taxonomy\/term\/5?_format=hal_json"
                    },
                    "type": {
                        "href": "http:\/\/drupal.org\/rest\/type\/taxonomy_term\/languages_supported"
                    }
                },
                "uuid": [
                    {
                        "value": "a4e125dc-5c50-46d4-9929-fbd36f3b1be1"
                    }
                ]
            }
        ]
    }
}