{
    "_links": {
        "self": {
            "href": "http:\/\/default\/admin\/appearance\/font\/6158?_format=hal_json"
        },
        "type": {
            "href": "http:\/\/drupal.org\/rest\/type\/font\/font"
        },
        "http:\/\/drupal.org\/rest\/relation\/font\/font\/field_classification": [
            {
                "href": "http:\/\/default\/taxonomy\/term\/7?_format=hal_json"
            }
        ],
        "http:\/\/drupal.org\/rest\/relation\/font\/font\/field_supported_languages": [
            {
                "href": "http:\/\/default\/taxonomy\/term\/6?_format=hal_json"
            }
        ]
    },
    "fid": [
        {
            "value": 6158
        }
    ],
    "uuid": [
        {
            "value": "371dd8fd-b3a3-4fdb-bfe4-72fd8eaa7aad"
        }
    ],
    "pid": [
        {
            "value": "google_fonts_api"
        }
    ],
    "url": [
        {
            "value": "https:\/\/www.google.com\/webfonts\/family?family=Cormorant Unicase&subset=latin-ext#regular"
        }
    ],
    "name": [
        {
            "value": "Cormorant Unicase regular (latin-ext)"
        }
    ],
    "css_family": [
        {
            "value": "Cormorant Unicase"
        }
    ],
    "css_style": [
        {
            "value": "normal"
        }
    ],
    "css_weight": [
        {
            "value": "normal"
        }
    ],
    "metadata": [
        {
            "value": "a:2:{s:4:\"path\";s:25:\"Cormorant Unicase:regular\";s:6:\"subset\";s:9:\"latin-ext\";}"
        }
    ],
    "created": [
        {
            "value": "2019-07-01T22:36:03+00:00",
            "format": "Y-m-d\\TH:i:sP"
        }
    ],
    "changed": [
        {
            "value": "2019-07-01T22:36:03+00:00",
            "format": "Y-m-d\\TH:i:sP"
        }
    ],
    "status": [
        {
            "value": false,
            "lang": "und"
        }
    ],
    "_embedded": {
        "http:\/\/drupal.org\/rest\/relation\/font\/font\/field_classification": [
            {
                "_links": {
                    "self": {
                        "href": "http:\/\/default\/taxonomy\/term\/7?_format=hal_json"
                    },
                    "type": {
                        "href": "http:\/\/drupal.org\/rest\/type\/taxonomy_term\/font_classification"
                    }
                },
                "uuid": [
                    {
                        "value": "95fd9bc0-aaf0-4ab7-9fde-1d696edc9579"
                    }
                ]
            }
        ],
        "http:\/\/drupal.org\/rest\/relation\/font\/font\/field_supported_languages": [
            {
                "_links": {
                    "self": {
                        "href": "http:\/\/default\/taxonomy\/term\/6?_format=hal_json"
                    },
                    "type": {
                        "href": "http:\/\/drupal.org\/rest\/type\/taxonomy_term\/languages_supported"
                    }
                },
                "uuid": [
                    {
                        "value": "8276fe76-fef7-4f2b-9992-d9bc09110c5c"
                    }
                ]
            }
        ]
    }
}