{
    "_links": {
        "self": {
            "href": "http:\/\/default\/admin\/appearance\/font\/7678?_format=hal_json"
        },
        "type": {
            "href": "http:\/\/drupal.org\/rest\/type\/font\/font"
        },
        "http:\/\/drupal.org\/rest\/relation\/font\/font\/field_classification": [
            {
                "href": "http:\/\/default\/taxonomy\/term\/15?_format=hal_json"
            }
        ],
        "http:\/\/drupal.org\/rest\/relation\/font\/font\/field_supported_languages": [
            {
                "href": "http:\/\/default\/taxonomy\/term\/16?_format=hal_json"
            }
        ]
    },
    "fid": [
        {
            "value": 7678
        }
    ],
    "uuid": [
        {
            "value": "ba4d5a7f-ffb9-44b6-a7b1-1e5ea2e5116d"
        }
    ],
    "pid": [
        {
            "value": "google_fonts_api"
        }
    ],
    "url": [
        {
            "value": "https:\/\/www.google.com\/webfonts\/family?family=Alegreya Sans&subset=greek#300"
        }
    ],
    "name": [
        {
            "value": "Alegreya Sans 300 (greek)"
        }
    ],
    "css_family": [
        {
            "value": "Alegreya Sans"
        }
    ],
    "css_style": [
        {
            "value": "normal"
        }
    ],
    "css_weight": [
        {
            "value": "300"
        }
    ],
    "metadata": [
        {
            "value": "a:2:{s:4:\"path\";s:17:\"Alegreya Sans:300\";s:6:\"subset\";s:5:\"greek\";}"
        }
    ],
    "created": [
        {
            "value": "2019-07-01T22:36:43+00:00",
            "format": "Y-m-d\\TH:i:sP"
        }
    ],
    "changed": [
        {
            "value": "2019-07-01T22:36:43+00:00",
            "format": "Y-m-d\\TH:i:sP"
        }
    ],
    "status": [
        {
            "value": false,
            "lang": "und"
        }
    ],
    "_embedded": {
        "http:\/\/drupal.org\/rest\/relation\/font\/font\/field_classification": [
            {
                "_links": {
                    "self": {
                        "href": "http:\/\/default\/taxonomy\/term\/15?_format=hal_json"
                    },
                    "type": {
                        "href": "http:\/\/drupal.org\/rest\/type\/taxonomy_term\/font_classification"
                    }
                },
                "uuid": [
                    {
                        "value": "0088518e-5e3f-45ea-ab71-5628d46a8aa7"
                    }
                ]
            }
        ],
        "http:\/\/drupal.org\/rest\/relation\/font\/font\/field_supported_languages": [
            {
                "_links": {
                    "self": {
                        "href": "http:\/\/default\/taxonomy\/term\/16?_format=hal_json"
                    },
                    "type": {
                        "href": "http:\/\/drupal.org\/rest\/type\/taxonomy_term\/languages_supported"
                    }
                },
                "uuid": [
                    {
                        "value": "bfa0c39b-316e-42d1-a0b1-02496f542f62"
                    }
                ]
            }
        ]
    }
}