{
    "_links": {
        "self": {
            "href": "http:\/\/default\/admin\/appearance\/font\/3150?_format=hal_json"
        },
        "type": {
            "href": "http:\/\/drupal.org\/rest\/type\/font\/font"
        },
        "http:\/\/drupal.org\/rest\/relation\/font\/font\/field_classification": [
            {
                "href": "http:\/\/default\/taxonomy\/term\/15?_format=hal_json"
            }
        ],
        "http:\/\/drupal.org\/rest\/relation\/font\/font\/field_supported_languages": [
            {
                "href": "http:\/\/default\/taxonomy\/term\/5?_format=hal_json"
            }
        ]
    },
    "fid": [
        {
            "value": 3150
        }
    ],
    "uuid": [
        {
            "value": "f2cc2809-2dae-446a-8c77-582c1ccf786e"
        }
    ],
    "pid": [
        {
            "value": "google_fonts_api"
        }
    ],
    "url": [
        {
            "value": "https:\/\/www.google.com\/webfonts\/family?family=Montserrat&subset=latin#700"
        }
    ],
    "name": [
        {
            "value": "Montserrat 700 (latin)"
        }
    ],
    "css_family": [
        {
            "value": "Montserrat"
        }
    ],
    "css_style": [
        {
            "value": "normal"
        }
    ],
    "css_weight": [
        {
            "value": "700"
        }
    ],
    "metadata": [
        {
            "value": "a:2:{s:4:\"path\";s:14:\"Montserrat:700\";s:6:\"subset\";s:5:\"latin\";}"
        }
    ],
    "created": [
        {
            "value": "2019-07-01T22:34:33+00:00",
            "format": "Y-m-d\\TH:i:sP"
        }
    ],
    "changed": [
        {
            "value": "2019-07-01T22:34:33+00:00",
            "format": "Y-m-d\\TH:i:sP"
        }
    ],
    "status": [
        {
            "value": false,
            "lang": "und"
        }
    ],
    "_embedded": {
        "http:\/\/drupal.org\/rest\/relation\/font\/font\/field_classification": [
            {
                "_links": {
                    "self": {
                        "href": "http:\/\/default\/taxonomy\/term\/15?_format=hal_json"
                    },
                    "type": {
                        "href": "http:\/\/drupal.org\/rest\/type\/taxonomy_term\/font_classification"
                    }
                },
                "uuid": [
                    {
                        "value": "0088518e-5e3f-45ea-ab71-5628d46a8aa7"
                    }
                ]
            }
        ],
        "http:\/\/drupal.org\/rest\/relation\/font\/font\/field_supported_languages": [
            {
                "_links": {
                    "self": {
                        "href": "http:\/\/default\/taxonomy\/term\/5?_format=hal_json"
                    },
                    "type": {
                        "href": "http:\/\/drupal.org\/rest\/type\/taxonomy_term\/languages_supported"
                    }
                },
                "uuid": [
                    {
                        "value": "a4e125dc-5c50-46d4-9929-fbd36f3b1be1"
                    }
                ]
            }
        ]
    }
}